Metadata-Version: 2.1
Name: bialign
Version: 0.3
Summary: Bialignment of RNAs and proteins
Home-page: https://github.com/s-will/BiAlign
Author: Sebastian Will
Author-email: sebastian.will@polytechnique.edu
Maintainer: Sebastian Will
Maintainer-email: sebastian.will@polytechnique.edu
License: UNKNOWN
Platform: UNKNOWN
Classifier: Development Status :: 5 - Production/Stable
Classifier: Intended Audience :: Science/Research
Classifier: License :: OSI Approved :: GNU General Public License v3 (GPLv3)
Classifier: Programming Language :: Python :: 3
Classifier: Programming Language :: Python :: 3 :: Only
Classifier: Topic :: Scientific/Engineering
License-File: LICENSE
